djangoldp_component/__init__.py
djangoldp_component/admin.py
djangoldp_component/apps.py
djangoldp_component/djangoldp_settings.py
djangoldp_component/models.py
djangoldp_component/settings.py
djangoldp_component/auth/__init__.py
djangoldp_component/auth/backends.py
djangoldp_component/migrations/0001_initial.py
djangoldp_component/migrations/0002_delete_dependency.py
djangoldp_component/migrations/0003_component_auto_menu.py
djangoldp_component/migrations/__init__.py
djangoldp_component-2.0.2.dist-info/METADATA
djangoldp_component-2.0.2.dist-info/WHEEL
djangoldp_component-2.0.2.dist-info/top_level.txt
djangoldp_component-2.0.2.dist-info/RECORD
