Metadata-Version: 2.1
Name: djangoldp-component
Version: 2.0.2
Summary: djangoldp component management package
Home-page: https://git.startinblox.com/applications/ontochain/component-registry
Author: Startin'blox
Author-email: jbaptiste@startinblox.com
License: MIT
Requires-Dist: djangoldp (~=3.0)
Requires-Dist: djangoldp-account (~=3.0)
